LICENSE
MANIFEST.in
README.rst
setup.py
django_typeahead/__init__.py
django_typeahead/admin.py
django_typeahead/apps.py
django_typeahead/views.py
django_typeahead/widgets.py
django_typeahead.egg-info/PKG-INFO
django_typeahead.egg-info/SOURCES.txt
django_typeahead.egg-info/dependency_links.txt
django_typeahead.egg-info/not-zip-safe
django_typeahead.egg-info/requires.txt
django_typeahead.egg-info/top_level.txt
django_typeahead/static/django_typeahead/css/typeahead.css
django_typeahead/static/django_typeahead/js/typeahead.js
django_typeahead/templates/django_typeahead/input.html
tests/__init__.py
tests/settings.py
tests/test_widget.py
tests/urls.py
tests/wsgi.py
tests/app/__init__.py
tests/app/settings.py