Metadata-Version: 1.1
Name: django-typeahead
Version: 1.0.1
Summary: Django app to add Typeahead.js based input elements.
Home-page: https://github.com/xvronny/django-typeahead/
Author: Ronny Hendrawan
Author-email: ronny.hendrawan@gmail.com
License: MIT License
Download-URL: https://github.com/xvronny/django-typeahead.git
Keywords: django-typeahead
Platform: UNKNOWN
Classifier: Development Status :: 3 - Alpha
Classifier: Intended Audience :: Developers
Classifier: Environment :: Web Environment
Classifier: Framework :: Django
Classifier: Framework :: Django :: 2.1
Classifier: Intended Audience :: Developers
Classifier: License :: OSI Approved :: MIT License
Classifier: Operating System :: OS Independent
Classifier: Programming Language :: Python
Classifier: Programming Language :: Python :: 3.5
Classifier: Programming Language :: Python :: 3.6
Classifier: Topic :: Software Development :: Libraries
Classifier: Topic :: Utilities
